hieralog/__init__.py
hieralog/hieralog.py
hieralog3-0.1.0.dist-info/METADATA
hieralog3-0.1.0.dist-info/WHEEL
hieralog3-0.1.0.dist-info/top_level.txt
hieralog3-0.1.0.dist-info/RECORD
