Metadata-Version: 2.1
Name: hieralog3
Version: 0.1.0
Summary: Hierarchical logging library with enhanced printing functions.
Home-page: https://github.com/yourusername/hieralog
Author: Your Name
Author-email: your.email@example.com
Classifier: Programming Language :: Python :: 3
Classifier: License :: OSI Approved :: MIT License
Requires-Python: >=3.6
Requires-Dist: tqdm
Requires-Dist: colorama
